LICENSE.txt
README.md
setup.cfg
setup.py
optimazing/__init__.py
optimazing/_optimizable_function.py
optimazing/_optimization_result.py
optimazing/_parameters.py
optimazing/losses.py
optimazing.egg-info/PKG-INFO
optimazing.egg-info/SOURCES.txt
optimazing.egg-info/dependency_links.txt
optimazing.egg-info/requires.txt
optimazing.egg-info/top_level.txt