Metadata-Version: 2.1
Name: optimazing
Version: 0.1.0
Summary: Wrapper around scipy.optimize.minimize
Home-page: https://github.com/thoinka/optimazing
Download-URL: https://github.com/thoinka/optimazing/archive/refs/tags/v0.0.1.tar.gz
Author: Tobias Hoinka
Author-email: thoinka@gmail.com
License: UNKNOWN
Keywords: Optimization,Scipy,Minimization
Platform: UNKNOWN
Classifier: Development Status :: 3 - Alpha
Classifier: Intended Audience :: Developers
Classifier: Topic :: Software Development :: Build Tools
Classifier: License :: OSI Approved :: MIT License
Classifier: Programming Language :: Python :: 3.8
Classifier: Programming Language :: Python :: 3.9
Classifier: Programming Language :: Python :: 3.10
License-File: LICENSE.txt
